stdin_processor/__init__.py
stdin_processor/append_command.py
stdin_processor/decode_command.py
stdin_processor/diff_command.py
stdin_processor/encode_command.py
stdin_processor/enum_command.py
stdin_processor/global_args.py
stdin_processor/hash_command.py
stdin_processor/hide_command.py
stdin_processor/lower_command.py
stdin_processor/main.py
stdin_processor/prepend_command.py
stdin_processor/processor.py
stdin_processor/remove_command.py
stdin_processor/replace_command.py
stdin_processor/reverse_command.py
stdin_processor/rotate_command.py
stdin_processor/show_command.py
stdin_processor/split_command.py
stdin_processor/strip_command.py
stdin_processor/style_command.py
stdin_processor/upper_command.py
stdin_processor/wrap_command.py
stdin_processor-0.0.67.dist-info/LICENSE.md
stdin_processor-0.0.67.dist-info/METADATA
stdin_processor-0.0.67.dist-info/WHEEL
stdin_processor-0.0.67.dist-info/entry_points.txt
stdin_processor-0.0.67.dist-info/top_level.txt
stdin_processor-0.0.67.dist-info/RECORD
