Metadata-Version: 2.1
Name: stdin-processor
Version: 0.0.67
Summary: String and Standard input manipulation CLI
Home-page: https://github.com/midnight-repo/stdin_processor
Author: midnight_repo
Author-email: midnight_repo@protonmail.com
License: GPL-3.0
Platform: UNKNOWN
License-File: LICENSE.md
Requires-Dist: typer
